{
    "type": "crafting_shaped",
    "pattern": [
        "FGF",
        "GEG",
        "XGX"
    ],
    "key": {
        "F": {
            "item": "minecraft:feather"
        },
        "E": {
            "item": "angelring:itemdiamondring"
        },
        "G": {
            "item": "minecraft:gold_block"
        },
        "X": {
            "item": "minecraft:blaze_rod"
        }
    },
    "result": {
        "item": "angelring:itemring",
        "count": 1
    }
}
